app_lib_py/ClassCurves.py
app_lib_py/ModulePredict.py
app_lib_py/__init__.py
app_lib_py-0.0.14.dist-info/LICENSE
app_lib_py-0.0.14.dist-info/METADATA
app_lib_py-0.0.14.dist-info/WHEEL
app_lib_py-0.0.14.dist-info/top_level.txt
app_lib_py-0.0.14.dist-info/RECORD
