Metadata-Version: 2.1
Name: app_lib_py
Version: 0.0.14
Summary: Example library for scientific software.
Home-page: https://github.com/RachelAlcraft/app-lib-py
Author: Rachel Alcraft
Author-email: rachelalcraft@gmail.com
Project-URL: Bug Tracker, https://github.com/RachelAlcraft/app-lib-py/issues
Project-URL: Documentation, https://rachelalcraft.github.io/app-lib-py
Project-URL: Application demo, https://app-lib-py.streamlit.app
Classifier: Programming Language :: Python :: 3
Classifier: License :: OSI Approved :: MIT License
Classifier: Operating System :: OS Independent
Requires-Python: >=3.6
License-File: LICENSE
